actual_lib/__init__.py
actual_lib/functions.py
odbn_test_lib-0.0.1.dist-info/METADATA
odbn_test_lib-0.0.1.dist-info/WHEEL
odbn_test_lib-0.0.1.dist-info/top_level.txt
odbn_test_lib-0.0.1.dist-info/RECORD
